mote/__init__.py
mote-0.0.4.dist-info/metadata.json
mote-0.0.4.dist-info/WHEEL
mote-0.0.4.dist-info/METADATA
mote-0.0.4.dist-info/DESCRIPTION.rst
mote-0.0.4.dist-info/top_level.txt
mote-0.0.4.dist-info/RECORD
